odoo10_addon_base_partner_merge-10.0.1.0.0-py2.7-nspkg.pth
odoo/addons/base_partner_merge/README.rst
odoo/addons/base_partner_merge/__init__.py
odoo/addons/base_partner_merge/__manifest__.py
odoo/addons/base_partner_merge/i18n/am.po
odoo/addons/base_partner_merge/i18n/ar.po
odoo/addons/base_partner_merge/i18n/base_partner_merge.pot
odoo/addons/base_partner_merge/i18n/ca.po
odoo/addons/base_partner_merge/i18n/cs.po
odoo/addons/base_partner_merge/i18n/da.po
odoo/addons/base_partner_merge/i18n/de.po
odoo/addons/base_partner_merge/i18n/el_GR.po
odoo/addons/base_partner_merge/i18n/es.po
odoo/addons/base_partner_merge/i18n/es_CR.po
odoo/addons/base_partner_merge/i18n/es_EC.po
odoo/addons/base_partner_merge/i18n/es_ES.po
odoo/addons/base_partner_merge/i18n/es_MX.po
odoo/addons/base_partner_merge/i18n/es_VE.po
odoo/addons/base_partner_merge/i18n/et.po
odoo/addons/base_partner_merge/i18n/fi.po
odoo/addons/base_partner_merge/i18n/fr.po
odoo/addons/base_partner_merge/i18n/gl.po
odoo/addons/base_partner_merge/i18n/hr_HR.po
odoo/addons/base_partner_merge/i18n/it.po
odoo/addons/base_partner_merge/i18n/lt.po
odoo/addons/base_partner_merge/i18n/nl.po
odoo/addons/base_partner_merge/i18n/nl_BE.po
odoo/addons/base_partner_merge/i18n/pl.po
odoo/addons/base_partner_merge/i18n/pt.po
odoo/addons/base_partner_merge/i18n/pt_BR.po
odoo/addons/base_partner_merge/i18n/pt_PT.po
odoo/addons/base_partner_merge/i18n/ro.po
odoo/addons/base_partner_merge/i18n/ru.po
odoo/addons/base_partner_merge/i18n/sl.po
odoo/addons/base_partner_merge/i18n/th.po
odoo/addons/base_partner_merge/i18n/tr.po
odoo/addons/base_partner_merge/i18n/vi.po
odoo/addons/base_partner_merge/static/description/icon.png
odoo/addons/base_partner_merge/views/base_partner_merge.xml
odoo/addons/base_partner_merge/wizard/__init__.py
odoo/addons/base_partner_merge/wizard/base_partner_merge.py
odoo/addons/base_partner_merge/wizard/validate_email.py
odoo10_addon_base_partner_merge-10.0.1.0.0.dist-info/DESCRIPTION.rst
odoo10_addon_base_partner_merge-10.0.1.0.0.dist-info/METADATA
odoo10_addon_base_partner_merge-10.0.1.0.0.dist-info/RECORD
odoo10_addon_base_partner_merge-10.0.1.0.0.dist-info/WHEEL
odoo10_addon_base_partner_merge-10.0.1.0.0.dist-info/metadata.json
odoo10_addon_base_partner_merge-10.0.1.0.0.dist-info/namespace_packages.txt
odoo10_addon_base_partner_merge-10.0.1.0.0.dist-info/top_level.txt
